neuralk_foundry_ce/VERSION.txt
neuralk_foundry_ce/__init__.py
neuralk_foundry_ce/datasets/__init__.py
neuralk_foundry_ce/datasets/base.py
neuralk_foundry_ce/datasets/industrial/__init__.py
neuralk_foundry_ce/datasets/industrial/abt_buy.py
neuralk_foundry_ce/datasets/industrial/best_buy_simple_categ.py
neuralk_foundry_ce/evaluation/__init__.py
neuralk_foundry_ce/evaluation/reporting/__init__.py
neuralk_foundry_ce/feature_engineering/__init__.py
neuralk_foundry_ce/feature_engineering/pairwise/__init__.py
neuralk_foundry_ce/feature_engineering/pairwise/pair_feature_generator.py
neuralk_foundry_ce/feature_engineering/preprocessing/__init__.py
neuralk_foundry_ce/feature_engineering/preprocessing/base.py
neuralk_foundry_ce/feature_engineering/preprocessing/categorical.py
neuralk_foundry_ce/feature_engineering/preprocessing/numerical.py
neuralk_foundry_ce/feature_engineering/vectorizer/__init__.py
neuralk_foundry_ce/feature_engineering/vectorizer/base.py
neuralk_foundry_ce/feature_engineering/vectorizer/identity.py
neuralk_foundry_ce/feature_engineering/vectorizer/tablevectorizer.py
neuralk_foundry_ce/feature_engineering/vectorizer/tabpfnvectorizer.py
neuralk_foundry_ce/feature_engineering/vectorizer/textencoder.py
neuralk_foundry_ce/feature_engineering/vectorizer/tfidfencoder.py
neuralk_foundry_ce/models/__init__.py
neuralk_foundry_ce/models/base.py
neuralk_foundry_ce/models/hyperopt.py
neuralk_foundry_ce/models/classifier/__init__.py
neuralk_foundry_ce/models/classifier/base.py
neuralk_foundry_ce/models/classifier/catboost.py
neuralk_foundry_ce/models/classifier/lightgbm.py
neuralk_foundry_ce/models/classifier/mlp.py
neuralk_foundry_ce/models/classifier/tabicl.py
neuralk_foundry_ce/models/classifier/tabpfn.py
neuralk_foundry_ce/models/classifier/xgboost.py
neuralk_foundry_ce/models/clustering/__init__.py
neuralk_foundry_ce/models/clustering/connected_components.py
neuralk_foundry_ce/models/embedder/__init__.py
neuralk_foundry_ce/models/embedder/base.py
neuralk_foundry_ce-0.0.2.dist-info/licenses/LICENSE
neuralk_foundry_ce-0.0.2.dist-info/METADATA
neuralk_foundry_ce-0.0.2.dist-info/WHEEL
neuralk_foundry_ce-0.0.2.dist-info/top_level.txt
neuralk_foundry_ce-0.0.2.dist-info/RECORD
