Metadata-Version: 2.4
Name: neuralk_foundry_ce
Version: 0.0.2
Summary: Package for representation of numerical data in format of integers or strings.
Author-email: Neuralk AI Research Team <alex@neuralk-ai.com>, Alexandre Abraham <alexandre.abraham@neuralk-ai.com>, Alexandre Pasquiou <alex@neuralk-ai.com>
Maintainer-email: Neuralk AI Research Team <alex@neuralk-ai.com>
Project-URL: Homepage, https://neuralk-ai.com
Project-URL: Repository, https://github.com/Neuralk-AI/neuralkFoundry-CE
Classifier: Development Status :: 3 - Alpha
Classifier: Intended Audience :: Science/Research
Classifier: Programming Language :: Python :: 3.10
Classifier: Programming Language :: Python :: 3.11
Classifier: Programming Language :: Python :: 3.12
Classifier: License :: OSI Approved :: Apache Software License
Classifier: Operating System :: OS Independent
Requires-Python: >=3.10
License-File: LICENSE
Requires-Dist: torch>=2.0.0
Requires-Dist: torchvision>=0.15
Requires-Dist: scipy>=1.15.0
Requires-Dist: scikit-learn>=1.6.0
Requires-Dist: torch_geometric>=2.6.1
Requires-Dist: openai>=1.61.1
Requires-Dist: skrub>=0.5.1
Requires-Dist: optuna>=4.2.1
Requires-Dist: lightgbm>=4.6.0
Requires-Dist: xgboost>=3.0.2
Requires-Dist: catboost>=1.2.8
Requires-Dist: tabpfn>=2.0.8
Requires-Dist: tabpfn_extensions
Requires-Dist: black==25.1.0
Requires-Dist: PyYAML==6.0.2
Requires-Dist: rich==13.9.4
Requires-Dist: memory_profiler==0.61.0
Requires-Dist: notebook>=7.4.2
Requires-Dist: pyarrow==18.1.0
Requires-Dist: fastparquet==2024.11.0
Requires-Dist: openml>=0.15.1
Requires-Dist: sphinx
Requires-Dist: sphinx_rtd_theme
Requires-Dist: sphinx_autodoc_typehints
Provides-Extra: dev
Requires-Dist: pytest; extra == "dev"
Dynamic: license-file
